<?xml version="1.0" encoding="UTF-8"?>
<persistence version="1.0" xmlns="http://java.sun.com/xml/ns/persistence">
  <persistence-unit name="hibernatePersistenceUnit">
    <class>edu.utpl.search.domain.ItemDetalleOCW</class>
    <properties>
      <property name="hibernate.hbm2ddl.auto" value="update"/>
      <property name="hibernate.dialect" value="org.hibernate.dialect.MySQL5InnoDBDialect"/>
    </properties>
    <mapping-file>META-INF/orm.xml</mapping-file>
  </persistence-unit>
</persistence>
